midv500models/__init__.py
midv500models/dataloaders.py
midv500models/inference.py
midv500models/metrics.py
midv500models/pre_trained_models.py
midv500models/preprocess_data.py
midv500models/schedulers.py
midv500models/train.py
midv500models/utils.py
midv500models-0.0.2.dist-info/LICENSE
midv500models-0.0.2.dist-info/METADATA
midv500models-0.0.2.dist-info/WHEEL
midv500models-0.0.2.dist-info/top_level.txt
midv500models-0.0.2.dist-info/RECORD
