Metadata-Version: 2.1
Name: midv500models
Version: 0.0.2
Summary: Document segmentation.
Home-page: https://github.com/ternaus/midv-500-models
Author: Vladimir Iglovikov
License: MIT
Platform: UNKNOWN
Classifier: License :: OSI Approved :: MIT License
Classifier: Intended Audience :: Developers
Classifier: Intended Audience :: Science/Research
Classifier: Operating System :: OS Independent
Classifier: Programming Language :: Python
Classifier: Programming Language :: Python :: 3
Classifier: Topic :: Software Development :: Libraries
Classifier: Topic :: Software Development :: Libraries :: Python Modules
Requires-Dist: albumentations
Requires-Dist: iglovikov-helper-functions
Requires-Dist: segmentation-models-pytorch
Requires-Dist: torch
Provides-Extra: test
Requires-Dist: pytest ; extra == 'test'
